umeng/UmengDownloaderMiddleware.py
umeng/UmengRequest.py
umeng/__init__.py
umeng/aop/__init__.py
umeng/aop/api/__init__.py
umeng/aop/api/base.py
umeng/aop/api/biz/UmengApptrackBackReportDataRequest.py
umeng/aop/api/biz/UmengApptrackGetActiveDetailDataRequest.py
umeng/aop/api/biz/UmengApptrackGetClickActiveDataRequest.py
umeng/aop/api/biz/UmengApptrackGetMonitoringListRequest.py
umeng/aop/api/biz/UmengApptrackGetMyEventDataRequest.py
umeng/aop/api/biz/UmengApptrackGetOrderAnalysisDataRequest.py
umeng/aop/api/biz/UmengApptrackGetPayAnalysisDataRequest.py
umeng/aop/api/biz/UmengApptrackGetPlanListRequest.py
umeng/aop/api/biz/UmengApptrackGetRegisterAnalysisDataRequest.py
umeng/aop/api/biz/UmengApptrackGetRegisterLoginDataRequest.py
umeng/aop/api/biz/UmengApptrackGetStayTrendDataRequest.py
umeng/aop/api/biz/UmengUappCreateAppRequest.py
umeng/aop/api/biz/UmengUappEventCreateRequest.py
umeng/aop/api/biz/UmengUappEventGetDataRequest.py
umeng/aop/api/biz/UmengUappEventGetUniqueUsersRequest.py
umeng/aop/api/biz/UmengUappEventListRequest.py
umeng/aop/api/biz/UmengUappEventParamGetDataRequest.py
umeng/aop/api/biz/UmengUappEventParamGetValueDurationListRequest.py
umeng/aop/api/biz/UmengUappEventParamGetValueListRequest.py
umeng/aop/api/biz/UmengUappEventParamListRequest.py
umeng/aop/api/biz/UmengUappGetActiveAccountsRequest.py
umeng/aop/api/biz/UmengUappGetActiveUsersByChannelOrVersionRequest.py
umeng/aop/api/biz/UmengUappGetActiveUsersRequest.py
umeng/aop/api/biz/UmengUappGetAllAppDataRequest.py
umeng/aop/api/biz/UmengUappGetAppCountRequest.py
umeng/aop/api/biz/UmengUappGetAppListRequest.py
umeng/aop/api/biz/UmengUappGetChannelDataRequest.py
umeng/aop/api/biz/UmengUappGetDailyDataRequest.py
umeng/aop/api/biz/UmengUappGetDurationsRequest.py
umeng/aop/api/biz/UmengUappGetLaunchesByChannelOrVersionRequest.py
umeng/aop/api/biz/UmengUappGetLaunchesRequest.py
umeng/aop/api/biz/UmengUappGetNewAccountsRequest.py
umeng/aop/api/biz/UmengUappGetNewUsersByChannelOrVersionRequest.py
scrapy_umeng-0.1.1.dist-info/METADATA
scrapy_umeng-0.1.1.dist-info/WHEEL
scrapy_umeng-0.1.1.dist-info/top_level.txt
scrapy_umeng-0.1.1.dist-info/RECORD
